{
    "TestDrive01": {
        "checkpoints": [
            {
                "steps": 6344,
                "file_path": "results\\testRun10\\TestDrive01\\TestDrive01-6344.onnx",
                "reward": -1.003140992448512,
                "creation_time": 1703119440.9576445,
                "auxillary_file_paths": [
                    "results\\testRun10\\TestDrive01\\TestDrive01-6344.pt"
                ]
            }
        ],
        "final_checkpoint": {
            "steps": 6344,
            "file_path": "results\\testRun10\\TestDrive01.onnx",
            "reward": -1.003140992448512,
            "creation_time": 1703119440.9576445,
            "auxillary_file_paths": [
                "results\\testRun10\\TestDrive01\\TestDrive01-6344.pt"
            ]
        }
    },
    "metadata": {
        "stats_format_version": "0.3.0",
        "mlagents_version": "0.30.0",
        "torch_version": "2.1.2+cpu"
    }
}