{
    "TestDrive01": {
        "checkpoints": [
            {
                "steps": 493236,
                "file_path": "results\\TrackingSomeTests10\\TestDrive01\\TestDrive01-493236.onnx",
                "reward": null,
                "creation_time": 1703358981.3968978,
                "auxillary_file_paths": [
                    "results\\TrackingSomeTests10\\TestDrive01\\TestDrive01-493236.pt"
                ]
            }
        ],
        "final_checkpoint": {
            "steps": 493236,
            "file_path": "results\\TrackingSomeTests10\\TestDrive01.onnx",
            "reward": null,
            "creation_time": 1703358981.3968978,
            "auxillary_file_paths": [
                "results\\TrackingSomeTests10\\TestDrive01\\TestDrive01-493236.pt"
            ]
        }
    },
    "metadata": {
        "stats_format_version": "0.3.0",
        "mlagents_version": "0.30.0",
        "torch_version": "2.1.2+cpu"
    }
}