{
    "TestDrive01": {
        "checkpoints": [
            {
                "steps": 41598,
                "file_path": "results\\TestRunAgain04\\TestDrive01\\TestDrive01-41598.onnx",
                "reward": null,
                "creation_time": 1703190867.2336047,
                "auxillary_file_paths": [
                    "results\\TestRunAgain04\\TestDrive01\\TestDrive01-41598.pt"
                ]
            }
        ],
        "final_checkpoint": {
            "steps": 41598,
            "file_path": "results\\TestRunAgain04\\TestDrive01.onnx",
            "reward": null,
            "creation_time": 1703190867.2336047,
            "auxillary_file_paths": [
                "results\\TestRunAgain04\\TestDrive01\\TestDrive01-41598.pt"
            ]
        }
    },
    "metadata": {
        "stats_format_version": "0.3.0",
        "mlagents_version": "0.30.0",
        "torch_version": "2.1.2+cpu"
    }
}